odoo/addons/module_change_auto_install/README.rst
odoo/addons/module_change_auto_install/__init__.py
odoo/addons/module_change_auto_install/__manifest__.py
odoo/addons/module_change_auto_install/patch.py
odoo/addons/module_change_auto_install/i18n/module_change_auto_install.pot
odoo/addons/module_change_auto_install/readme/CONFIGURE.rst
odoo/addons/module_change_auto_install/readme/CONTRIBUTORS.rst
odoo/addons/module_change_auto_install/readme/DESCRIPTION.rst
odoo/addons/module_change_auto_install/readme/DEVELOP.rst
odoo/addons/module_change_auto_install/readme/INSTALL.rst
odoo/addons/module_change_auto_install/static/description/icon.png
odoo/addons/module_change_auto_install/static/description/index.html
odoo12_addon_module_change_auto_install-12.0.1.0.1.99.dev4.dist-info/METADATA
odoo12_addon_module_change_auto_install-12.0.1.0.1.99.dev4.dist-info/WHEEL
odoo12_addon_module_change_auto_install-12.0.1.0.1.99.dev4.dist-info/top_level.txt
odoo12_addon_module_change_auto_install-12.0.1.0.1.99.dev4.dist-info/RECORD
